virtual_tiff/__init__.py
virtual_tiff/codecs.py
virtual_tiff/constants.py
virtual_tiff/imagecodecs.py
virtual_tiff/parser.py
virtual_tiff/py.typed
virtual_tiff/utils.py
virtual_tiff/vendor/xarray/zarr.py
virtual_tiff-0.2.1.dist-info/METADATA
virtual_tiff-0.2.1.dist-info/WHEEL
virtual_tiff-0.2.1.dist-info/entry_points.txt
virtual_tiff-0.2.1.dist-info/licenses/LICENSE.txt
virtual_tiff-0.2.1.dist-info/RECORD
