Metadata-Version: 2.4
Name: virtual_tiff
Version: 0.2.1
Summary: A parser intended for use with VirtualiZarr to create virtual Zarr stores from TIFFs
Author-email: Max Jones <14077947+maxrjones@users.noreply.github.com>
License-Expression: MIT
License-File: LICENSE.txt
Keywords: COG,Python,cloud-native,compressed,ndimensional-arrays,tiff,zarr
Classifier: Development Status :: 4 - Beta
Classifier: Programming Language :: Python
Classifier: Programming Language :: Python :: 3.11
Classifier: Programming Language :: Python :: 3.12
Requires-Python: >=3.11
Requires-Dist: async-tiff
Requires-Dist: imagecodecs
Requires-Dist: imagecodecs-numcodecs
Requires-Dist: obstore
Requires-Dist: virtualizarr>=2.0
Requires-Dist: zarr
